cloudmesh_pearl-4.3.2-py3.8-nspkg.pth
cloudmesh/pearl/Pearl.py
cloudmesh/pearl/__init__.py
cloudmesh/pearl/__version__.py
cloudmesh/pearl/command/__init__.py
cloudmesh/pearl/command/pearl.py
cloudmesh_pearl-4.3.2.dist-info/LICENSE
cloudmesh_pearl-4.3.2.dist-info/METADATA
cloudmesh_pearl-4.3.2.dist-info/WHEEL
cloudmesh_pearl-4.3.2.dist-info/namespace_packages.txt
cloudmesh_pearl-4.3.2.dist-info/top_level.txt
cloudmesh_pearl-4.3.2.dist-info/RECORD
